{"cameraMode":{"drawMode":0,"name":"Shaded","section":"Shading Mode"},"sceneLighting":false,"audioPlay":false,"sceneViewState":{"m_AlwaysRefresh":false,"showFog":true,"showSkybox":false,"showFlares":true,"showImageEffects":true,"showParticleSystems":true,"showVisualEffectGraphs":true,"m_FxEnabled":true},"in2DMode":false,"pivot":{"x":-0.11812587827444077,"y":2.586036443710327,"z":3.058244466781616},"rotation":{"x":-0.013159391470253468,"y":0.9589208364486694,"z":-0.2793898582458496,"w":-0.04582098126411438},"size":0.8197275996208191,"orthographic":false}